<?xml version="1.0" encoding="UTF-8"?>
<!-- JBoss, Home of Professional Open Source Copyright 2013, Red Hat, Inc. 
	and/or its affiliates, and individual contributors by the @authors tag. See 
	the copyright.txt in the distribution for a full listing of individual contributors. 
	Licensed under the Apache License, Version 2.0 (the "License"); you may not 
	use this file except in compliance with the License. You may obtain a copy 
	of the License at http://www.apache.org/licenses/LICENSE-2.0 Unless required 
	by applicable law or agreed to in writing, software distributed under the 
	License is distributed on an "AS IS" BASIS, WITHOUT WARRANTIES OR CONDITIONS 
	OF ANY KIND, either express or implied. See the License for the specific 
	language governing permissions and limitations under the License. -->
<!-- This file is not required if you don't need any extra configuration. -->
<faces-config version="2.0" xmlns="http://java.sun.com/xml/ns/javaee"
	xmlns:xsi="http://www.w3.org/2001/XMLSchema-instance"
	xsi:schemaLocation="
        http://java.sun.com/xml/ns/javaee
        http://java.sun.com/xml/ns/javaee/web-facesconfig_2_0.xsd">
        
	<navigation-rule>
		<navigation-case>
			<from-outcome>exames-pesquisarLaudoUnico</from-outcome>
			<to-view-id>/pages/exames/patologia/pesquisarLaudoUnico.xhtml</to-view-id>
		<redirect/></navigation-case>
	</navigation-rule>
        
	<navigation-rule>
		<navigation-case>
			<from-outcome>exames-laboratorioHemocentroCRUD</from-outcome>
			<to-view-id>/pages/exames/cadastrosapoio/laboratorioHemocentroCRUD.xhtml</to-view-id>
		<redirect/></navigation-case>
	</navigation-rule>
	
	<navigation-rule>
		<navigation-case>
			<from-outcome>exames-relatorioRelacaoExamesUnidade</from-outcome>
			<to-view-id>/pages/exames/relatorios/relatorioRelacaoExamesUnidade.xhtml</to-view-id>
		<redirect/></navigation-case>
	</navigation-rule>
        
	<navigation-rule>
		<navigation-case>
			<from-outcome>exames-medicoAtendimentoExternoCRUD</from-outcome>
			<to-view-id>/pages/exames/cadastrosapoio/medicoAtendimentoExternoCRUD.xhtml</to-view-id>
		<redirect/></navigation-case>
	</navigation-rule>        
        
	<navigation-rule>
		<navigation-case>
			<from-outcome>exames-relatorioLaudoUnicoPdf</from-outcome>
			<to-view-id>/pages/exames/patologia/relatorios/relatorioLaudoUnicoPdf.xhtml</to-view-id>
		<redirect/></navigation-case>
	</navigation-rule>
        
        
	<navigation-rule>				
		<navigation-case>
			<from-outcome>exames-pesquisarArquivosProcessados</from-outcome>
			<to-view-id>/pages/exames/contratualizacao/pesquisarArquivosProcessados.xhtml</to-view-id>
		<redirect/></navigation-case>
	</navigation-rule>
        
        
	<navigation-rule>
		<navigation-case>
			<from-outcome>exames-manterLoteExamesCrud</from-outcome>
			<to-view-id>/pages/exames/cadastrosapoio/manterLoteExamesCrud.xhtml</to-view-id>
		<redirect/></navigation-case>
	</navigation-rule>
        
	<navigation-rule>
		<navigation-case>
			<from-outcome>exames-pesquisaLoteExames</from-outcome>
			<to-view-id>/pages/exames/pesquisa/pesquisaLoteExames.xhtml</to-view-id>
		<redirect/></navigation-case>
	</navigation-rule>

    <navigation-rule>
		<navigation-case>
			<from-outcome>exames-protocoloEntregaExames</from-outcome>
			<to-view-id>/pages/exames/relatorios/imprimirProtocoloEntregaExamesPdf.xhtml</to-view-id>
		<redirect/></navigation-case>
	</navigation-rule>
        
	<navigation-rule>
		<navigation-case>
			<from-outcome>exames-pesquisaCadastroExamesUnidade</from-outcome>
			<to-view-id>/pages/exames/pesquisa/pesquisaCadastroExamesUnidade.xhtml</to-view-id>
		<redirect/></navigation-case>
	</navigation-rule>
        
	<navigation-rule>
		<navigation-case>
			<from-outcome>exames-manterOrdemExamesPOL</from-outcome>
			<to-view-id>/pages/exames/manterOrdemExamesPOL.xhtml</to-view-id>
		<redirect/></navigation-case>
	</navigation-rule>
	
	<navigation-rule>
		<navigation-case>
			<from-outcome>exames-pesquisarOrdemExamesPOL</from-outcome>
			<to-view-id>/pages/exames/pesquisa/pesquisarOrdemExamesPOL.xhtml</to-view-id>
		<redirect/></navigation-case>
	</navigation-rule>
	
        
	<navigation-rule>
		<navigation-case>
			<from-outcome>exames-pesquisaExameSituacao</from-outcome>
			<to-view-id>/pages/exames/pesquisa/pesquisaExameSituacao.xhtml</to-view-id>
		<redirect/></navigation-case>
	</navigation-rule>
        
	<navigation-rule>
		<navigation-case>
			<from-outcome>exames-relatorioExamesPendentes</from-outcome>
			<to-view-id>/pages/exames/patologia/relatorioExamesPendentes.xhtml</to-view-id>
		<redirect/></navigation-case>
	</navigation-rule>
	
	<navigation-rule>
		<navigation-case>
			<from-outcome>exames-relatorioExamesPendentesPdf</from-outcome>
			<to-view-id>/pages/exames/patologia/relatorioExamesPendentesPdf.xhtml</to-view-id>
		<redirect/></navigation-case>
	</navigation-rule>
	
	<navigation-rule>
		<navigation-case>
			<from-outcome>exames-relatorioExameSituacaoPdf</from-outcome>
			<to-view-id>/pages/exames/relatorios/relatorioExameSituacaoPdf.xhtml</to-view-id>
		<redirect/></navigation-case>
	</navigation-rule>
        
	<navigation-rule>
		<navigation-case>
			<from-outcome>exames-relatorioCaracteristicasResultadosPdf</from-outcome>
			<to-view-id>/pages/exames/relatorios/relatorioCaracteristicasResultadosPdf.xhtml</to-view-id>
		<redirect/></navigation-case>
	</navigation-rule>
        
	<navigation-rule>
		<navigation-case>
			<from-outcome>exames-manterCaracteristicaResultado</from-outcome>
			<to-view-id>/pages/exames/cadastrosapoio/manterCaracteristicaResultado.xhtml</to-view-id>
		<redirect/></navigation-case>
	</navigation-rule>
        
	<navigation-rule>
		<navigation-case>
			<from-outcome>exames-manterGrupoCaracteristica</from-outcome>
			<to-view-id>/pages/exames/cadastrosapoio/manterGrupoCaracteristica.xhtml</to-view-id>
		<redirect/></navigation-case>
	</navigation-rule>
        
	<navigation-rule>
		<navigation-case>
			<from-outcome>exames-pesquisaTituloResultadoPadrao</from-outcome>
			<to-view-id>/pages/exames/pesquisa/pesquisaTituloResultadoPadrao.xhtml</to-view-id>
		<redirect/></navigation-case>
	</navigation-rule>
        
	<navigation-rule>
		<navigation-case>
			<from-outcome>exames-manterTituloResultadoPadrao</from-outcome>
			<to-view-id>/pages/exames/cadastrosapoio/manterTituloResultadoPadrao.xhtml</to-view-id>
		<redirect/></navigation-case>
	</navigation-rule>
        
	<navigation-rule>
		<navigation-case>
			<from-outcome>exames-pesquisaCampoLaudo</from-outcome>
			<to-view-id>/pages/exames/pesquisa/pesquisaCampoLaudo.xhtml</to-view-id>
		<redirect/></navigation-case>
	</navigation-rule>
        
	<navigation-rule>
		<navigation-case>
			<from-outcome>exames-manterCampoLaudo</from-outcome>
			<to-view-id>/pages/exames/cadastrosapoio/manterCampoLaudo.xhtml</to-view-id>
		<redirect/></navigation-case>
	</navigation-rule>
        
	<navigation-rule>
		<navigation-case>
			<from-outcome>exames-manterValorNormalidadeCampo</from-outcome>
			<to-view-id>/pages/exames/cadastrosapoio/manterValorNormalidadeCampo.xhtml</to-view-id>
		<redirect/></navigation-case>
	</navigation-rule>
        
	<navigation-rule>
		<navigation-case>
			<from-outcome>exames-manterSinonimoCampoLaudo</from-outcome>
			<to-view-id>/pages/exames/cadastrosapoio/manterSinonimoCampoLaudo.xhtml</to-view-id>
		<redirect/></navigation-case>
	</navigation-rule>

	<navigation-rule>
		<navigation-case>
			<from-outcome>exames-resultadoPadraoCRUD</from-outcome>
			<to-view-id>/pages/exames/cadastrosapoio/resultadoPadraoCRUD.xhtml</to-view-id>
		<redirect/></navigation-case>
	</navigation-rule>

	<navigation-rule>
		<navigation-case>
			<from-outcome>exames-mascaraExamesEditor</from-outcome>
			<to-view-id>/pages/exames/mascaraExames/mascaraExamesEditor.xhtml</to-view-id>
		<redirect/></navigation-case>
	</navigation-rule>

	<navigation-rule>
		<navigation-case>
			<from-outcome>exames-manterMascarasLaudosCRUD</from-outcome>
			<to-view-id>/pages/exames/cadastrosapoio/manterMascarasLaudosCRUD.xhtml</to-view-id>
		<redirect/></navigation-case>
	</navigation-rule>

	<navigation-rule>
		<navigation-case>
			<from-outcome>exames-pesquisaMascarasLaudos</from-outcome>
			<to-view-id>/pages/exames/pesquisa/pesquisaMascarasLaudos.xhtml</to-view-id>
		<redirect/></navigation-case>
	</navigation-rule>

	<navigation-rule>
		<navigation-case>
			<from-outcome>exames-manterAssociacaoRequisitanteQuestionario</from-outcome>
			<to-view-id>/pages/exames/questionario/manterAssociacaoRequisitanteQuestionario.xhtml</to-view-id>
		<redirect/></navigation-case>
	</navigation-rule>

	<navigation-rule>
		<navigation-case>
			<from-outcome>exames-manterQuestionarioPesquisa</from-outcome>
			<to-view-id>/pages/exames/questionario/manterQuestionarioPesquisa.xhtml</to-view-id>
		<redirect/></navigation-case>
	</navigation-rule>

	<navigation-rule>
		<navigation-case>
			<from-outcome>exames-manterQuestoesQuestionario</from-outcome>
			<to-view-id>/pages/exames/questionario/manterQuestoesQuestionario.xhtml</to-view-id>
		<redirect/></navigation-case>
	</navigation-rule>
	
	<navigation-rule>
		<navigation-case>
			<from-outcome>exames-manterExameQuestionario</from-outcome>
			<to-view-id>/pages/exames/questionario/manterExameQuestionario.xhtml</to-view-id>
		<redirect/></navigation-case>
	</navigation-rule>
	
	<navigation-rule>
		<navigation-case>
			<from-outcome>exames-mantemInfoComplementaresVinculadasExame</from-outcome>
			<to-view-id>/pages/exames/cadastrosapoio/mantemInfoComplementaresVinculadasExame.xhtml</to-view-id>
		<redirect/></navigation-case>
	</navigation-rule>

	<navigation-rule>
		<navigation-case>
			<from-outcome>exames-manterAssociacaoOrigemQuestionario</from-outcome>
			<to-view-id>/pages/exames/questionario/manterAssociacaoOrigemQuestionario.xhtml</to-view-id>
		<redirect/></navigation-case>
	</navigation-rule>

	<navigation-rule>
		<navigation-case>
			<from-outcome>exames-pesquisaSolicitacaoInternacaoUnidadesFechadas</from-outcome>
			<to-view-id>/pages/exames/pesquisa/pesquisaSolicitacaoInternacaoUnidadesFechadas.xhtml</to-view-id>
		<redirect/></navigation-case>
	</navigation-rule>

	<navigation-rule>
		<navigation-case>
			<from-outcome>exames-monitorarColetasEmergenciaPesquisa</from-outcome>
			<to-view-id>/pages/exames/pesquisa/monitorarColetasEmergenciaPesquisa.xhtml</to-view-id>
		<redirect/></navigation-case>
	</navigation-rule>

	<navigation-rule>
		<navigation-case>
			<from-outcome>exames-monitorPendenciasExames</from-outcome>
			<to-view-id>/pages/exames/monitorPendenciasExames.xhtml</to-view-id>
		<redirect/></navigation-case>
	</navigation-rule>

	<navigation-rule>
		<navigation-case>
			<from-outcome>exames-pesquisaExameSituacao</from-outcome>
			<to-view-id>/pages/exames/pesquisa/pesquisaExameSituacao.xhtml</to-view-id>
		<redirect/></navigation-case>
	</navigation-rule>

	<navigation-rule>
		<navigation-case>
			<from-outcome>exames-agruparCaracteristicaExame</from-outcome>
			<to-view-id>/pages/exames/cadastrosapoio/agruparCaracteristicaExame.xhtml</to-view-id>
		<redirect/></navigation-case>
	</navigation-rule>

	<navigation-rule>
		<navigation-case>
			<from-outcome>exames-pesquisaCadastroExamesUnidade</from-outcome>
			<to-view-id>/pages/exames/pesquisa/pesquisaCadastroExamesUnidade.xhtml</to-view-id>
		<redirect/></navigation-case>
	</navigation-rule>

	<navigation-rule>
		<navigation-case>
			<from-outcome>exames-emitirRelacaoPacientesInternadosExamesRealizar</from-outcome>
			<to-view-id>/pages/exames/relatorios/emitirRelacaoPacientesInternadosExamesRealizar.xhtml</to-view-id>
		<redirect/></navigation-case>
	</navigation-rule>

	<navigation-rule>
		<navigation-case>
			<from-outcome>exames-visualizarRelatorioPacientesInternadosExamesRealizarPdf</from-outcome>
			<to-view-id>/pages/exames/relatorios/visualizarRelatorioPacientesInternadosExamesRealizarPdf.xhtml</to-view-id>
		<redirect/></navigation-case>
	</navigation-rule>

	<navigation-rule>
		<navigation-case>
			<from-outcome>exames-relatorioFluxogramaPdf</from-outcome>
			<to-view-id>/pages/exames/relatorios/relatorioFluxogramaPdf.xhtml</to-view-id>
		<redirect/></navigation-case>
	</navigation-rule>

	<navigation-rule>
		<navigation-case>
			<from-outcome>exames-pesquisaFluxograma</from-outcome>
			<to-view-id>/pages/exames/pesquisa/pesquisaFluxograma.xhtml</to-view-id>
		<redirect/></navigation-case>
	</navigation-rule>

	<navigation-rule>
		<navigation-case>
			<from-outcome>exames-motivoCancelamentoList</from-outcome>
			<to-view-id>/pages/exames/cadastrosapoio/motivoCancelamentoList.xhtml</to-view-id>
		<redirect/></navigation-case>
	</navigation-rule>

	<navigation-rule>
		<navigation-case>
			<from-outcome>exames-relatorioMotivoCancelamentoExamesPdf</from-outcome>
			<to-view-id>/pages/exames/relatorios/relatorioMotivoCancelamentoExamesPdf.xhtml</to-view-id>
		<redirect/></navigation-case>
	</navigation-rule>

	<navigation-rule>
		<navigation-case>
			<from-outcome>exames-manterDadosBasicosExamesPesquisa</from-outcome>
			<to-view-id>/pages/exames/cadastrosapoio/manterDadosBasicosExamesPesquisa.xhtml</to-view-id>
		<redirect/></navigation-case>
	</navigation-rule>

	<navigation-rule>
		<navigation-case>
			<from-outcome>exames-manterDadosBasicosExamesCRUD</from-outcome>
			<to-view-id>/pages/exames/cadastrosapoio/manterDadosBasicosExamesCRUD.xhtml</to-view-id>
		<redirect/></navigation-case>
	</navigation-rule>

	<navigation-rule>
		<navigation-case>
			<from-outcome>exames-sinonimosExameList</from-outcome>
			<to-view-id>/pages/exames/cadastrosapoio/sinonimosExameList.xhtml</to-view-id>
		<redirect/></navigation-case>
	</navigation-rule>

	<navigation-rule>
		<navigation-case>
			<from-outcome>exames-manterExamesMaterialDependenteCRUD</from-outcome>
			<to-view-id>/pages/exames/cadastrosapoio/manterExamesMaterialDependenteCRUD.xhtml</to-view-id>
		<redirect/></navigation-case>
	</navigation-rule>

	<navigation-rule>
		<navigation-case>
			<from-outcome>exames-manterUnidadesExecutorasExamesCRUD</from-outcome>
			<to-view-id>/pages/exames/cadastrosapoio/manterUnidadesExecutorasExamesCRUD.xhtml</to-view-id>
		<redirect/></navigation-case>
	</navigation-rule>


	<navigation-rule>
		<navigation-case>
			<from-outcome>exames-manterPermissoesUnidadesSolicitantesCRUD</from-outcome>
			<to-view-id>/pages/exames/cadastrosapoio/manterPermissoesUnidadesSolicitantesCRUD.xhtml</to-view-id>
		<redirect/></navigation-case>
	</navigation-rule>
	
	<navigation-rule>
		<navigation-case>
			<from-outcome>exames-manterRestringirPedidoServidorCRUD</from-outcome>
			<to-view-id>/pages/exames/cadastrosapoio/manterRestringirPedidoServidorCRUD.xhtml</to-view-id>
		<redirect/></navigation-case>
	</navigation-rule>	
	
	<navigation-rule>
		<navigation-case>
			<from-outcome>exames-manterRestringirPedidoEspecialidadeCRUD</from-outcome>
			<to-view-id>/pages/exames/cadastrosapoio/manterRestringirPedidoEspecialidadeCRUD.xhtml</to-view-id>
		<redirect/></navigation-case>
	</navigation-rule>
	
	<navigation-rule>
		<navigation-case>
			<from-outcome>exames-manterMetodoUnfExameCRUD</from-outcome>
			<to-view-id>/pages/exames/cadastrosapoio/manterMetodoUnfExameCRUD.xhtml</to-view-id>
		<redirect/></navigation-case>
	</navigation-rule>


	<navigation-rule>
		<navigation-case>
			<from-outcome>exames-manterRecomendacaoRealizacaoExameCRUD</from-outcome>
			<to-view-id>/pages/exames/cadastrosapoio/manterRecomendacaoRealizacaoExameCRUD.xhtml</to-view-id>
		<redirect/></navigation-case>
	</navigation-rule>

	<navigation-rule>
		<navigation-case>
			<from-outcome>exames-manterProvaExameCRUD</from-outcome>
			<to-view-id>/pages/exames/cadastrosapoio/manterProvaExameCRUD.xhtml</to-view-id>
		<redirect/></navigation-case>
	</navigation-rule>

	<navigation-rule>
		<navigation-case>
			<from-outcome>exames-manterHorarioColetaExameCRUD</from-outcome>
			<to-view-id>/pages/exames/cadastrosapoio/manterHorarioColetaExameCRUD.xhtml</to-view-id>
		<redirect/></navigation-case>
	</navigation-rule>

	<navigation-rule>
		<navigation-case>
			<from-outcome>exames-manterConselhosProfissionaisExameCRUD</from-outcome>
			<to-view-id>/pages/exames/cadastrosapoio/manterConselhosProfissionaisExameCRUD.xhtml</to-view-id>
		<redirect/></navigation-case>
	</navigation-rule>

	<navigation-rule>
		<navigation-case>
			<from-outcome>exames-manterEquipamentosExecutamExame</from-outcome>
			<to-view-id>/pages/exames/cadastrosapoio/manterEquipamentosExecutamExame.xhtml</to-view-id>
		<redirect/></navigation-case>
	</navigation-rule>

	<navigation-rule>
		<navigation-case>
			<from-outcome>exames-manterIntervaloColetaCRUD</from-outcome>
			<to-view-id>/pages/exames/cadastrosapoio/manterIntervaloColetaCRUD.xhtml</to-view-id>
		<redirect/></navigation-case>
	</navigation-rule>

	<navigation-rule>
		<navigation-case>
			<from-outcome>exames-manterExamesMaterialAnaliseCRUD</from-outcome>
			<to-view-id>/pages/exames/cadastrosapoio/manterExamesMaterialAnaliseCRUD.xhtml</to-view-id>
		<redirect/></navigation-case>
	</navigation-rule>

	<navigation-rule>
		<navigation-case>
			<from-outcome>exames-manterNumeroCopiasResultadoExame</from-outcome>
			<to-view-id>/pages/exames/cadastrosapoio/manterNumeroCopiasResultadoExame.xhtml</to-view-id>
		<redirect/></navigation-case>
	</navigation-rule>

	<navigation-rule>
		<navigation-case>
			<from-outcome>exames-manterExameReflexo</from-outcome>
			<to-view-id>/pages/exames/cadastrosapoio/manterExameReflexo.xhtml</to-view-id>
		<redirect/></navigation-case>
	</navigation-rule>


	<navigation-rule>
		<navigation-case>
			<from-outcome>exames-solicitacaoExameCRUD</from-outcome>
			<to-view-id>/pages/exames/solicitacao/solicitacaoExameCRUD.xhtml</to-view-id>
		<redirect/></navigation-case>
	</navigation-rule>

	<navigation-rule>
		<navigation-case>
			<from-outcome>exames-pesquisaExames</from-outcome>
			<to-view-id>/pages/exames/pesquisa/pesquisaExames.xhtml</to-view-id>
		<redirect/></navigation-case>
	</navigation-rule>

	<navigation-rule>
		<navigation-case>
			<from-outcome>exames-pesquisaEntregaExames</from-outcome>
			<to-view-id>/pages/exames/pesquisa/pesquisaEntregaExames.xhtml</to-view-id>
		<redirect/></navigation-case>
	</navigation-rule>
	
	<navigation-rule>
		<navigation-case>
			<from-outcome>exames-pesquisaProtocoloEntregaExames</from-outcome>
			<to-view-id>/pages/exames/protocoloEntrega/pesquisaProtocoloEntregaExames.xhtml</to-view-id>
		<redirect/></navigation-case>
	</navigation-rule>

	<navigation-rule>
		<navigation-case>
			<from-outcome>exames-atendimentoExternoCRUD</from-outcome>
			<to-view-id>/pages/exames/atendimentoExternoCRUD.xhtml</to-view-id>
		<redirect/></navigation-case>
	</navigation-rule>
	
	
	<navigation-rule>
		<navigation-case>
			<from-outcome>exames-listarAgendamento</from-outcome>
			<to-view-id>/pages/exames/agendamento/listarExamesAgendamentoSelecao.xhtml</to-view-id>
		<redirect/></navigation-case>
	</navigation-rule>
	
	
	
<navigation-rule>
		<navigation-case>
			<from-outcome>exames-detalharItemSolicitacaoExame</from-outcome>
			<to-view-id>/pages/exames/solicitacao/detalharItemSolicitacaoExame.xhtml</to-view-id>
		<redirect/></navigation-case>
	</navigation-rule>

	<navigation-rule>
		<navigation-case>
			<from-outcome>exames-visualizarResultado</from-outcome>
			<to-view-id>/pages/paciente/prontuarioonline/visualizacaoResultadoExame.xhtml</to-view-id>
		<redirect/></navigation-case>
	</navigation-rule>
	
	<navigation-rule>
		<navigation-case>
			<from-outcome>exames-visualizarResultadoHist</from-outcome>
			<to-view-id>/pages/paciente/prontuarioonline/visualizacaoResultadoExameHist.xhtml</to-view-id>
		<redirect/></navigation-case>
	</navigation-rule>	

	<navigation-rule>
		<navigation-case>
			<from-outcome>exames-resultadoNotaAdicional</from-outcome>
			<to-view-id>/pages/exames/cadastroResultadosNotaAdicional.xhtml</to-view-id>
		<redirect/></navigation-case>
	</navigation-rule>

	<navigation-rule>
		<navigation-case>
			<from-outcome>exames-tipoAmostraConvenioCRUD</from-outcome>
			<to-view-id>/pages/exames/cadastrosapoio/tipoAmostraConvenioCRUD.xhtml</to-view-id>
		<redirect/></navigation-case>
	</navigation-rule>
	
	<navigation-rule>
		<navigation-case>
			<from-outcome>exames-consultarResultadoNotaAdicional</from-outcome>
			<to-view-id>/pages/exames/consultarResultadoNotaAdicional.xhtml</to-view-id>
		<redirect/></navigation-case>
	</navigation-rule>
	
	<navigation-rule>
		<navigation-case>
			<from-outcome>exames-atendimentoDiversoList</from-outcome>
			<to-view-id>/pages/exames/cadastrosapoio/atendimentoDiversoList.xhtml</to-view-id>
		<redirect/></navigation-case>
	</navigation-rule>
	
	<navigation-rule>
		<navigation-case>
			<from-outcome>exames-atendimentoDiverso</from-outcome>
			<to-view-id>/pages/exames/cadastrosapoio/atendimentoDiverso.xhtml</to-view-id>
		<redirect/></navigation-case>
	</navigation-rule>
	
	<navigation-rule>
		<navigation-case>
			<from-outcome>exames-mantemInfoComplementaresVinculadasExame</from-outcome>
			<to-view-id>/pages/exames/cadastrosapoio/mantemInfoComplementaresVinculadasExame.xhtml</to-view-id>
		<redirect/></navigation-case>
	</navigation-rule>	
	
	<navigation-rule>
		<navigation-case>
			<from-outcome>exames-manterAssociacaoOrigemQuestionario</from-outcome>
			<to-view-id>/pages/exames/questionario/manterAssociacaoOrigemQuestionario.xhtml</to-view-id>
		<redirect/></navigation-case>
	</navigation-rule>	
	
	<navigation-rule>
		<navigation-case>
			<from-outcome>exames-manterExameQuestionario</from-outcome>
			<to-view-id>/pages/exames/questionario/manterExameQuestionario.xhtml</to-view-id>
		<redirect/></navigation-case>
	</navigation-rule>
	
	<navigation-rule>
		<navigation-case>
			<from-outcome>exames-cancelarExamesResponsabilidadeSolicitante</from-outcome>
			<to-view-id>/pages/exames/cancelarExamesResponsabilidadeSolicitante.xhtml</to-view-id>
		<redirect/></navigation-case>
	</navigation-rule>	
	
	
	<navigation-rule>
		<navigation-case>
			<from-outcome>exames-pesquisaDetalhesSolicitacaoExame</from-outcome>
			<to-view-id>/pages/exames/solicitacao/pesquisaDetalhesSolicitacaoExame.xhtml</to-view-id>
		<redirect/></navigation-case>
	</navigation-rule>	
	
	
	<navigation-rule>
		<navigation-case>
			<from-outcome>exames-ajustarNumeracaoUnicaAmostra</from-outcome>
			<to-view-id>/pages/exames/ajustarNumeracaoUnicaAmostra.xhtml</to-view-id>
		<redirect/></navigation-case>
	</navigation-rule>	
	
	<navigation-rule>
		<navigation-case>
			<from-outcome>exames-copiarNumeracaoUnicaAmostra</from-outcome>
			<to-view-id>/pages/exames/copiarNumeracaoUnicaAmostra.xhtml</to-view-id>
		<redirect/></navigation-case>
	</navigation-rule>	
	
	<navigation-rule>
		<navigation-case>
			<from-outcome>exames-pesquisaCancelarExamesAreaExecutora</from-outcome>
			<to-view-id>/pages/exames/pesquisaCancelarExamesAreaExecutora.xhtml</to-view-id>
		<redirect/></navigation-case>
	</navigation-rule>	
	
	<navigation-rule>
		<navigation-case>
			<from-outcome>exames-cancelarExamesAreaExecutora</from-outcome>
			<to-view-id>/pages/exames/cancelarExamesAreaExecutora.xhtml</to-view-id>
		<redirect/></navigation-case>
	</navigation-rule>	

	<navigation-rule>
		<navigation-case>
			<from-outcome>exames-listarAmostrasSolicitacaoRecebimento</from-outcome>
			<to-view-id>/pages/exames/listarAmostrasSolicitacaoRecebimento.xhtml</to-view-id>
		<redirect/></navigation-case>
	</navigation-rule>
	
	<navigation-rule>
		<navigation-case>
			<from-outcome>exames-informarSolicitacaoExameDigitacao</from-outcome>
			<to-view-id>/pages/exames/informarSolicitacaoExameDigitacao.xhtml</to-view-id>
		<redirect/></navigation-case>
	</navigation-rule>
	
	<navigation-rule>
		<navigation-case>
			<from-outcome>exames-relatorioListarSolicitacoesColeta</from-outcome>
			<to-view-id>/pages/exames/relatorios/relatorioListarSolicitacoesColetarPdf.xhtml</to-view-id>
		<redirect/></navigation-case>
	</navigation-rule>	
	
	
	<navigation-rule>
		<navigation-case>
			<from-outcome>exames-monitorarColetasEmergenciaPesquisa</from-outcome>
			<to-view-id>/pages/exames/pesquisa/monitorarColetasEmergenciaPesquisa.xhtml</to-view-id>
		<redirect/></navigation-case>
	</navigation-rule>	
	
	
	<navigation-rule>
		<navigation-case>
			<from-outcome>exames-cancelarExamesColeta</from-outcome>
			<to-view-id>/pages/exames/cancelarExamesColeta.xhtml</to-view-id>
		<redirect/></navigation-case>
	</navigation-rule>	
	
	<navigation-rule>
		<navigation-case>
			<from-outcome>exames-pesquisaCancelarExamesColeta</from-outcome>
			<to-view-id>/pages/exames/pesquisa/pesquisaCancelarExamesColeta.xhtml</to-view-id>
		<redirect/></navigation-case>
	</navigation-rule>	
	
	<navigation-rule>
		<navigation-case>
			<from-outcome>exames-pesquisaAmostrasExames</from-outcome>
			<to-view-id>/pages/exames/solicitacao/pesquisaAmostrasExames.xhtml</to-view-id>
		<redirect/></navigation-case>
	</navigation-rule>	
	
	<navigation-rule>
		<navigation-case>
			<from-outcome>exames-pesquisaAgendaExamesHorarios</from-outcome>
			<to-view-id>/pages/exames/coleta/pesquisaAgendaExamesHorarios.xhtml</to-view-id>
		<redirect/></navigation-case>
	</navigation-rule>	
	
	<navigation-rule>
		<navigation-case>
			<from-outcome>exames-pesquisaProtocolarPaciente</from-outcome>
			<to-view-id>/pages/exames/protocolopaciente/pesquisaProtocolarPaciente.xhtml</to-view-id>
		<redirect/></navigation-case>
	</navigation-rule>
	
	<navigation-rule>
		<navigation-case>
			<from-outcome>exames-voltarPesquisa</from-outcome>
			<to-view-id>/pages/exames/pesquisa/pesquisaEntregaExames.xhtml</to-view-id>
		<redirect/></navigation-case>
	</navigation-rule>
	
	<navigation-rule>
		<navigation-case>
			<from-outcome>exames-voltarPesquisa-protocolo</from-outcome>
			<to-view-id>/pages/exames/protocoloEntrega/pesquisaProtocoloEntregaExames.xhtml</to-view-id>
		<redirect/></navigation-case>
	</navigation-rule>
	
	<navigation-rule>
		<navigation-case>
			<from-outcome>exames-protocolarPacienteCRUD</from-outcome>
			<to-view-id>/pages/exames/protocolopaciente/protocolarPacienteCRUD.xhtml</to-view-id>
		<redirect/></navigation-case>
	</navigation-rule>
	
	<navigation-rule>
		<navigation-case>
			<from-outcome>exames-cargaExamesInterfaceamento</from-outcome>
			<to-view-id>/pages/exames/cargaExamesInterfaceamento.xhtml</to-view-id>
		<redirect/></navigation-case>
	</navigation-rule>	
	
	<navigation-rule>
		<navigation-case>
			<from-outcome>exames-liberaLimitacaoExameSolicitacao</from-outcome>
			<to-view-id>/pages/exames/liberaLimitacaoExameSolicitacao.xhtml</to-view-id>
		<redirect/></navigation-case>
	</navigation-rule>		
	
	<navigation-rule>
		<navigation-case>
			<from-outcome>exames-informacaoColetaAmostra</from-outcome>
			<to-view-id>/pages/exames/coleta/informacaoColetaAmostra.xhtml</to-view-id>
		<redirect/></navigation-case>
	</navigation-rule>	
	
	<navigation-rule>
		<navigation-case>
			<from-outcome>exames-gestaoCartasRecoletaList</from-outcome>
			<to-view-id>/pages/exames/gestaoCartasRecoletaList.xhtml</to-view-id>
		<redirect/></navigation-case>
	</navigation-rule>
	
	<navigation-rule>
		<navigation-case>
			<from-outcome>exames-listarExamesCriteriosSelecionados</from-outcome>
			<to-view-id>/pages/exames/listarExamesCriteriosSelecionados.xhtml</to-view-id>
		<redirect/></navigation-case>
	</navigation-rule>		
	
	<navigation-rule>
		<navigation-case>
			<from-outcome>exames-editarExameSolicitadoAreaExecutora</from-outcome>
			<to-view-id>/pages/exames/editarExameSolicitadoAreaExecutora.xhtml</to-view-id>
		<redirect/></navigation-case>
	</navigation-rule>

	<navigation-rule>
		<navigation-case>
			<from-outcome>exames-gestaoCartasRecoletaList</from-outcome>
			<to-view-id>/pages/exames/gestaoCartasRecoletaList.xhtml</to-view-id>
		<redirect/></navigation-case>
	</navigation-rule>
		
	<navigation-rule>
		<navigation-case>
			<from-outcome>exames-relatorioEtiquetaEnvelopePaciente</from-outcome>
			<to-view-id>/pages/exames/agendamento/relatorioEtiquetaEnvelopePaciente.xhtml</to-view-id>
		<redirect/></navigation-case>
	</navigation-rule>		
	
	<navigation-rule>
		<navigation-case>
			<from-outcome>exames-relatorioTicketExamesAreaExecutoraPdf</from-outcome>
			<to-view-id>/pages/exames/relatorios/relatorioTicketExamesAreaExecutoraPdf.xhtml</to-view-id>
		<redirect/></navigation-case>
	</navigation-rule>
	
	
	<navigation-rule>
		<navigation-case>
			<from-outcome>exames-laudounico</from-outcome>
			<to-view-id>/pages/exames/patologia/laudoUnico.xhtml</to-view-id>
		<redirect/></navigation-case>
	</navigation-rule>			
	
<navigation-rule>
		<navigation-case>
			<from-outcome>RelMapaTrabalhoBioqController</from-outcome>
			<to-view-id>/pages/exames/relatorios/relatorioMapaTrabalhoBioquimicaPdf.xhtml</to-view-id>
		<redirect/></navigation-case>
	</navigation-rule>	
	
	<navigation-rule>
		<navigation-case>
			<from-outcome>RelMapaTrabalhoSoroController</from-outcome>
			<to-view-id>/pages/exames/relatorios/relatorioMapaTrabalhoBioquimicaPdf.xhtml</to-view-id>
		<redirect/></navigation-case>
	</navigation-rule>
	
	<navigation-rule>
		<navigation-case>
			<from-outcome>RelMapaTrabBioEquController</from-outcome>
			<to-view-id>/pages/exames/relatorios/relatorioMapaTrabalhoBioquimicaEquPdf.xhtml</to-view-id>
		<redirect/></navigation-case>
	</navigation-rule>	
	
	<navigation-rule>
		<navigation-case>
			<from-outcome>RelMapaTrabHemoCD4Controller</from-outcome>
			<to-view-id>/pages/exames/relatorios/relatorioMapaTrabalhoHematologiaCD4Pdf.xhtml</to-view-id>
		<redirect/></navigation-case>
	</navigation-rule>	
	
	<navigation-rule>
		<navigation-case>
			<from-outcome>RelMapaTrabalhoHemoController</from-outcome>
			<to-view-id>/pages/exames/relatorios/relatorioMapaTrabalhoHemoculturaPdf.xhtml</to-view-id>
		<redirect/></navigation-case>
	</navigation-rule>	
	
	<navigation-rule>
		<navigation-case>
			<from-outcome>RelMapaTrabalhoEPFController</from-outcome>
			<to-view-id>/pages/exames/relatorios/relatorioMapaTrabalhoEpfPdf.xhtml</to-view-id>
		<redirect/></navigation-case>
	</navigation-rule>	
	
	<navigation-rule>
		<navigation-case>
			<from-outcome>RelMapaTrabalhoUroController</from-outcome>
			<to-view-id>/pages/exames/relatorios/relatorioMapaTrabalhoUroculturaPdf.xhtml</to-view-id>
		<redirect/></navigation-case>
	</navigation-rule>	
	
	<navigation-rule>
		<navigation-case>
			<from-outcome>RelMapaTrabalhoHemaController</from-outcome>
			<to-view-id>/pages/exames/relatorios/relatorioMapaTrabalhoHemaPdf.xhtml</to-view-id>
		<redirect/></navigation-case>
	</navigation-rule>	
	
	<navigation-rule>
		<navigation-case>
			<from-outcome>exames-emissaoMapaTrabalho</from-outcome>
			<to-view-id>/pages/exames/emissaoMapaTrabalho.xhtml</to-view-id>
		<redirect/></navigation-case>
	</navigation-rule>	
	
	<navigation-rule>
		<navigation-case>
			<from-outcome>exames-resultadoMamografiaList</from-outcome>
			<to-view-id>/pages/exames/sismama/resultadoMamografiaList.xhtml</to-view-id>
		<redirect/></navigation-case>
	</navigation-rule>	
	
	<navigation-rule>
		<navigation-case>
			<from-outcome>exames-resultadoMamografiaCRUD</from-outcome>
			<to-view-id>/pages/exames/sismama/resultadoMamografiaCRUD.xhtml</to-view-id>
		<redirect/></navigation-case>
	</navigation-rule>
	
	<navigation-rule>
		<navigation-case>
			<from-outcome>exames-resultadoExameHistopatologico</from-outcome>
			<to-view-id>/pages/exames/sismama/resultadoExameHistopatologico.xhtml</to-view-id>
		<redirect/></navigation-case>
	</navigation-rule>
	
	<navigation-rule>
		<navigation-case>
			<from-outcome>exames-pesquisarSolicitacaoDiversos</from-outcome>
			<to-view-id>/pages/exames/coleta/pesquisarSolicitacaoDiversos.xhtml</to-view-id>
		<redirect/></navigation-case>
	</navigation-rule>
	
	<navigation-rule>
		<navigation-case>
			<from-outcome>exames-pesquisaRespostaQuestionario</from-outcome>
			<to-view-id>/pages/exames/questionario/pesquisaRespostaQuestionario.xhtml</to-view-id>
		<redirect/></navigation-case>
	</navigation-rule>
	
	
	
	<navigation-rule>
		<navigation-case>
			<from-outcome>exames-gerarProtocoloEntregaExames</from-outcome>
			<to-view-id>/pages/exames/protocoloEntrega/protocoloEntregaExames.xhtml</to-view-id>
		<redirect/></navigation-case>
	</navigation-rule> 
	
	
	
	<navigation-rule>
		<navigation-case>
			<from-outcome>exames-visualizarQuestionarioSismamaBiopsia</from-outcome>
			<to-view-id>/pages/exames/sismama/visualizarQuestionarioSismamaBiopsia.xhtml</to-view-id>
		<redirect/></navigation-case>
	</navigation-rule>
	
	<navigation-rule>
		<navigation-case>
			<from-outcome>exames-verificaQuestoesSismama</from-outcome>
			<to-view-id>/pages/exames/sismama/verificaQuestoesSismama.xhtml</to-view-id>
		<redirect/></navigation-case>
	</navigation-rule>	
	
	<navigation-rule>
		<navigation-case>
			<from-outcome>exames-relatorioMonitorPendenciaPdf</from-outcome>
			<to-view-id>/pages/exames/relatorios/relatorioMonitorPendenciaPdf.xhtml</to-view-id>
		<redirect/></navigation-case>
	</navigation-rule>
	
	<navigation-rule>
		<navigation-case>
			<from-outcome>exames-listaImpressaoLaudos</from-outcome>
			<to-view-id>/pages/exames/patologia/listaImpressaoLaudos.xhtml</to-view-id>
		<redirect/></navigation-case>
	</navigation-rule>
	
	<navigation-rule>
		<navigation-case>
			<from-outcome>exames-listaRealizacaoExamesPatologia</from-outcome>
			<to-view-id>/pages/exames/patologia/listaRealizacaoExamesPatologia.xhtml</to-view-id>
		<redirect/></navigation-case>
	</navigation-rule>		
	
	<navigation-rule>
		<navigation-case>
			<from-outcome>exames-trocarResidentePatologistaRealzExame</from-outcome>
			<to-view-id>/pages/exames/patologia/trocarResidentePatologistaRealzExame.xhtml</to-view-id>
		<redirect/></navigation-case>
	</navigation-rule>		
		<navigation-rule>
		<navigation-case>
			<from-outcome>exames-previaForm</from-outcome>
			<to-view-id>/pages/exames/mascaraExames/previaFormMascaraExamesEditor.xhtml</to-view-id>
		<redirect/></navigation-case>
	</navigation-rule>		
	
	<navigation-rule>
		<navigation-case>
			<from-outcome>exames-cadastroResultadoPadraoLaudo</from-outcome>
			<to-view-id>/pages/exames/mascaraExames/cadastroResultadoPadraoLaudo.xhtml</to-view-id>
		<redirect/></navigation-case>
	</navigation-rule>		
	
	<navigation-rule>
		<navigation-case>
			<from-outcome>exames-previaPdf</from-outcome>
			<to-view-id>/pages/exames/mascaraExames/previaMascaraExamesEditor.xhtml</to-view-id>
		<redirect/></navigation-case>
	</navigation-rule>
	
	<navigation-rule>
		<navigation-case>
			<from-outcome>exames-mascaraExamesEditor</from-outcome>
			<to-view-id>/pages/exames/mascaraExames/mascaraExamesEditor.xhtml</to-view-id>
		<redirect/></navigation-case>
	</navigation-rule>		
			

	<navigation-rule>
		<navigation-case>
			<from-outcome>exames-relatorioLaudoUnicoPdf</from-outcome>
			<to-view-id>/pages/exames/patologia/relatorios/relatorioLaudoUnicoPdf.xhtml</to-view-id>
		<redirect/></navigation-case>
	</navigation-rule>	
	
	<navigation-rule>
		<navigation-case>
			<from-outcome>exames-manterNomenclaturaGenerica</from-outcome>
			<to-view-id>/pages/exames/patologia/cadastrosapoio/manterNomenclaturaGenerica.xhtml</to-view-id>
		<redirect/></navigation-case>
	</navigation-rule>	
	
	<navigation-rule>
		<navigation-case>
			<from-outcome>exames-manterNomenclaturaEspecifica</from-outcome>
			<to-view-id>/pages/exames/patologia/cadastrosapoio/manterNomenclaturaEspecifica.xhtml</to-view-id>
		<redirect/></navigation-case>
	</navigation-rule>
	
	<navigation-rule>
		<navigation-case>
			<from-outcome>exames-manterConfiguracaoExamesList</from-outcome>
			<to-view-id>/pages/exames/patologia/cadastrosapoio/manterConfiguracaoExamesList.xhtml</to-view-id>
		<redirect/></navigation-case>
	</navigation-rule>
	
	<navigation-rule>
		<navigation-case>
			<from-outcome>exames-detalhesItemExames</from-outcome>
			<to-view-id>/pages/exames/solicitacao/detalharItemSolicitacaoExame.xhtml</to-view-id>
		<redirect/></navigation-case>
	</navigation-rule>
	
	<navigation-rule>
		<navigation-case>
			<from-outcome>exames-manterCaracteristicaMaterialAnalise</from-outcome>
			<to-view-id>/pages/exames/patologia/cadastrosapoio/manterCaracteristicaMaterialAnalise.xhtml</to-view-id>
		<redirect/></navigation-case>
	</navigation-rule>		
	
	<navigation-rule>
		<navigation-case>
			<from-outcome>exames-resultadoPadraoCRUD</from-outcome>
			<to-view-id>/pages/exames/cadastrosapoio/resultadoPadraoCRUD.xhtml</to-view-id>
		<redirect/></navigation-case>
	</navigation-rule>		
	
	
	<navigation-rule>
		<navigation-case>
			<from-outcome>exames-pesquisaExamesHistorico</from-outcome>
			<to-view-id>/pages/exames/pesquisa/pesquisaExamesHistorico.xhtml</to-view-id>
		<redirect/></navigation-case>
	</navigation-rule>	
	
	<navigation-rule>
		<navigation-case>
			<from-outcome>exames-manterHorarioRotinaColetaCRUD</from-outcome>
			<to-view-id>/pages/exames/cadastrosapoio/manterHorarioRotinaColetaCRUD.xhtml</to-view-id>
		<redirect/></navigation-case>
	</navigation-rule>
		
	<navigation-rule>
		<navigation-case>
			<from-outcome>exames-imprimirResultadoExamePdf</from-outcome>
			<to-view-id>/pages/exames/imprimirResultadoExamePdf.xhtml</to-view-id>
		<redirect/></navigation-case>
	</navigation-rule>	

	<navigation-rule>
		<navigation-case>
			<from-outcome>exames-solicitacaoExameList</from-outcome>
			<to-view-id>/pages/exames/solicitacao/solicitacaoExameList.xhtml</to-view-id>
		<redirect/></navigation-case>
	</navigation-rule>	

	<navigation-rule>
		<navigation-case>
			<from-outcome>exames-exibirTicketPaciente</from-outcome>
			<to-view-id>/pages/exames/solicitacao/visualizarTicketPaciente.xhtml</to-view-id>
		<redirect/></navigation-case>
	</navigation-rule>	

	<navigation-rule>
		<navigation-case>
			<from-outcome>exames-voltarParaListaSolicitacao</from-outcome>
			<to-view-id>/pages/exames/solicitacao/solicitacaoExameList.xhtml</to-view-id>
		<redirect/></navigation-case>
	</navigation-rule>	
	
	<navigation-rule>
		<navigation-case>
			<from-outcome>exames-consultaHorarioLivreParaAgendar</from-outcome>
			<to-view-id>/pages/exames/agendamento/consultaHorariosLivresExame.xhtml</to-view-id>
		<redirect/></navigation-case>
	</navigation-rule>
	
	<navigation-rule>
		<navigation-case>
			<from-outcome>exames-responsavelContaCRUD</from-outcome>
			<to-view-id>/pages/exames/cadastrosapoio/responsavelCRUD.xhtml</to-view-id>
		<redirect/></navigation-case>
	</navigation-rule>  
	
	

	
	
	
	
	<!-- =================================================================================================================== -->
	<!-- ATENÇÃO: Coloque os valores para as variáveis de redirect com o nome 
		do módulo junto: Ex: casca-pesquisarPermissoes -->
	<!-- =================================================================================================================== -->

</faces-config>